assets/courses/comp-arch/verilog/rtl/memory/d_flipflop_behavioral.v
module d_ff_master_slave_behavioral (
    input  wire d,
    input  wire clk,
    output reg  q
);
    reg master;

    // Master latch: transparent while clk = 0, holds while clk = 1
    always @(*)
        if (!clk) master = d;

    // Slave latch: transparent while clk = 1, holds while clk = 0
    always @(*)
        if (clk) q = master;
endmodule

assets/courses/comp-arch/verilog/tb/memory/d_flipflop_behavioral.v
`timescale 1ns/1ps

module tb_d_ff_master_slave_behavioral;
    reg  d, clk;
    wire q;

    d_ff_master_slave_behavioral dut (.d(d), .clk(clk), .q(q));

    initial clk = 0;
    always #10 clk = ~clk;   // 20ns period

    initial begin
        $dumpfile("sim/d_flipflop_behavioral.vcd");
        $dumpvars(0, tb_d_ff_master_slave_behavioral);

        d = 0;
        #10  d = 1;   // set well before edge @10
        #12 d = 0;   // set well before edge @20 (master reopens then)
        #20 d = 1;   // set well before edge @40
        #8 d = 0;   // set well before edge @60
        #22 $finish;
    end

    initial
        $monitor("t=%0t  clk=%b  d=%b  |  q=%b", $time, clk, d, q);
endmodule

assets/courses/comp-arch/verilog/sim/d_flipflop_behavioral.vcd
$date
	Wed Jul  8 16:52:13 2026
$end
$version
	Icarus Verilog
$end
$timescale
	1ps
$end
$scope module tb_d_ff_master_slave_behavioral $end
$var wire 1 ! q $end
$var reg 1 " clk $end
$var reg 1 # d $end
$scope module dut $end
$var wire 1 " clk $end
$var wire 1 # d $end
$var reg 1 $ master $end
$var reg 1 ! q $end
$upscope $end
$upscope $end
$enddefinitions $end
$comment Show the parameter values. $end
$dumpall
$end
#0
$dumpvars
0$
0#
0"
x!
$end
#10000
0!
1#
1"
#20000
1$
0"
#22000
0$
0#
#30000
1"
#40000
0"
#42000
1$
1#
#50000
1!
0#
1"
#60000
0$
0"
#70000
0!
1"
