assets/courses/comp-arch/verilog/rtl/memory/sr_latch.v
module sr_latch (
	input wire s,
	input wire r,
	output wire q,
	output wire q_n
);
	wire s_n, r_n;

	not(s_n, s);
	not(r_n, r);

	nand(q, s_n, q_n);
	nand(q_n, r_n, q);
endmodule

assets/courses/comp-arch/verilog/rtl/memory/d_latch.v
module d_latch (
	input wire d,
	input wire en,
	output wire q,
	output wire q_n
);
	wire d_n;
	wire s, r;

	not(d_n, d);
	and(s, d, en);
	and(r, d_n, en);

	sr_latch srlatch (
		.s(s),
		.r(r),
		.q(q),
		.q_n(q_n)
	);
endmodule

assets/courses/comp-arch/verilog/rtl/memory/d_flipflop.v
module d_flipflop (
	input wire d,
	input wire clk,
	output wire q,
	output wire q_n
);

	wire clk_n;
	wire _q, _q_n;

	not(clk_n, clk);

	d_latch master (
		.d(d),
		.en(clk_n),
		.q(_q),
		.q_n(_q_n)
	);

	d_latch slave (
		.d(_q),
		.en(clk),
		.q(q),
		.q_n(q_n)
	);
endmodule

assets/courses/comp-arch/verilog/tb/memory/d_flipflop.v
module d_flipflop_tb;
	reg d, clk;
	wire q, q_n;

	d_flipflop dff(
		.d(d),
		.clk(clk),
		.q(q),
		.q_n(q_n)
	);

	always #5 clk = ~clk;

	initial begin
		$dumpfile("sim/d_flipflop.vcd");
		$dumpvars(0, d_flipflop_tb);

		clk = 0;
		d <= 0; #5;
		$display("[%0t] d=%b clk=%b -> q=%b (expected 0) q_n=%b", $time, d, clk, q, q_n);

		d <= 1; #10;
		$display("[%0t] d=%b clk=%b -> q=%b (expected 1) q_n=%b", $time, d, clk, q, q_n);

		d <= 0; #5;
		$display("[%0t] d=%b clk=%b -> q=%b (expected 0) q_n=%b", $time, d, clk, q, q_n);

		d <= 1; #12;
		$display("[%0t] d=%b clk=%b -> q=%b (expected 0) q_n=%b", $time, d, clk, q, q_n);

		d <= 0; #3;
		$display("[%0t] d=%b clk=%b -> q=%b (expected 1) q_n=%b", $time, d, clk, q, q_n);

		d <= 1; #17;
		$display("[%0t] d=%b clk=%b -> q=%b (expected 1) q_n=%b", $time, d, clk, q, q_n);

		d <= 0; #10;
		$display("[%0t] d=%b clk=%b -> q=%b (expected 1) q_n=%b", $time, d, clk, q, q_n);

		d <= 1; #3;
		$display("[%0t] d=%b clk=%b -> q=%b (expected 0) q_n=%b", $time, d, clk, q, q_n);

		$finish;

	end
endmodule

assets/courses/comp-arch/verilog/sim/d_flipflop.vcd
$date
	Wed Jul  8 16:41:20 2026
$end
$version
	Icarus Verilog
$end
$timescale
	1s
$end
$scope module d_flipflop_tb $end
$var wire 1 ! q_n $end
$var wire 1 " q $end
$var reg 1 # clk $end
$var reg 1 $ d $end
$scope module dff $end
$var wire 1 # clk $end
$var wire 1 % clk_n $end
$var wire 1 $ d $end
$var wire 1 ! q_n $end
$var wire 1 " q $end
$var wire 1 & _q_n $end
$var wire 1 ' _q $end
$scope module master $end
$var wire 1 $ d $end
$var wire 1 ( d_n $end
$var wire 1 % en $end
$var wire 1 ) r $end
$var wire 1 * s $end
$var wire 1 & q_n $end
$var wire 1 ' q $end
$scope module srlatch $end
$var wire 1 ' q $end
$var wire 1 & q_n $end
$var wire 1 ) r $end
$var wire 1 + r_n $end
$var wire 1 * s $end
$var wire 1 , s_n $end
$upscope $end
$upscope $end
$scope module slave $end
$var wire 1 ' d $end
$var wire 1 - d_n $end
$var wire 1 # en $end
$var wire 1 . r $end
$var wire 1 / s $end
$var wire 1 ! q_n $end
$var wire 1 " q $end
$scope module srlatch $end
$var wire 1 " q $end
$var wire 1 ! q_n $end
$var wire 1 . r $end
$var wire 1 0 r_n $end
$var wire 1 / s $end
$var wire 1 1 s_n $end
$upscope $end
$upscope $end
$upscope $end
$upscope $end
$enddefinitions $end
$comment Show the parameter values. $end
$dumpall
$end
#0
$dumpvars
11
10
0/
0.
1-
1,
0+
0*
1)
1(
0'
1&
1%
0$
0#
x"
x!
$end
#5
0(
1$
0"
1+
1!
0)
00
0%
1.
1#
#10
0&
0-
1'
0,
1*
10
1%
0.
0#
#15
1(
0$
0!
1,
1"
0*
01
0%
1/
1#
#20
0,
0(
1*
1$
0-
1'
0&
1+
0)
11
1%
0/
0#
#25
1,
0*
01
0%
1/
1#
#30
0,
1*
11
1%
0/
0#
#32
1-
0'
1&
0+
1)
1,
1(
0*
0$
#35
0(
1$
0"
1+
1!
0)
00
0%
1.
1#
#40
0&
0-
1'
0,
1*
10
1%
0.
0#
#45
0!
1,
1"
0*
01
0%
1/
1#
#50
0,
1*
11
1%
0/
0#
#52
1-
0'
1&
0+
1)
1,
1(
0*
0$
#55
0"
1+
1!
0)
00
0%
1.
1#
#60
0+
1)
10
1%
0.
0#
#62
0&
0-
1+
1'
0)
0,
0(
1*
1$
#65
0!
1,
1"
0*
01
0%
1/
1#
