assets/courses/comp-arch/verilog/rtl/memory/sr_latch.v
module sr_latch (
	input wire s,
	input wire r,
	output wire q,
	output wire q_n
);
	wire s_n, r_n;

	not(s_n, s);
	not(r_n, r);

	nand(q, s_n, q_n);
	nand(q_n, r_n, q);
endmodule

assets/courses/comp-arch/verilog/rtl/memory/d_latch.v
module d_latch (
	input wire d,
	input wire en,
	output wire q,
	output wire q_n
);
	wire d_n;
	wire s, r;

	not(d_n, d);
	and(s, d, en);
	and(r, d_n, en);

	sr_latch srlatch (
		.s(s),
		.r(r),
		.q(q),
		.q_n(q_n)
	);
endmodule

assets/courses/comp-arch/verilog/rtl/memory/d_flipflop_async.v
module d_flipflop_async (
	input wire d,
	input wire clk,
	input wire r,
	output wire q,
	output wire q_n
);

	wire clk_n;
	wire r_n;
	wire _q, _q_n;

	not(clk_n, clk);
	not(r_n, r);

	d_latch master (
		.d(d),
		.en(clk_n),
		.q(_q),
		.q_n(_q_n)
	);

	wire _q_or_reset, _clk;

	and(_q_or_reset, _q, r_n);
	or(_clk, clk, r);

	d_latch slave (
		.d(_q_or_reset),
		.en(_clk),
		.q(q),
		.q_n(q_n)
	);
endmodule

assets/courses/comp-arch/verilog/rtl/memory/reg_8b.v
module reg_8b (
	input wire [7:0] in,
	input wire clk,
	input wire r,
	output wire [7:0] out
);
	d_flipflop_async dffa0(.d(in[0]), .clk(clk), .r(r), .q(out[0]));
	d_flipflop_async dffa1(.d(in[1]), .clk(clk), .r(r), .q(out[1]));
	d_flipflop_async dffa2(.d(in[2]), .clk(clk), .r(r), .q(out[2]));
	d_flipflop_async dffa3(.d(in[3]), .clk(clk), .r(r), .q(out[3]));
	d_flipflop_async dffa4(.d(in[4]), .clk(clk), .r(r), .q(out[4]));
	d_flipflop_async dffa5(.d(in[5]), .clk(clk), .r(r), .q(out[5]));
	d_flipflop_async dffa6(.d(in[6]), .clk(clk), .r(r), .q(out[6]));
	d_flipflop_async dffa7(.d(in[7]), .clk(clk), .r(r), .q(out[7]));
endmodule

assets/courses/comp-arch/verilog/tb/memory/reg_8b.v
module reg_8b_tb;
	reg [7:0] in;
	reg clk, r;
	wire [7:0] out;

	reg_8b uut(
		.in(in),
		.clk(clk),
		.r(r),
		.out(out)
	);

	initial begin
		$dumpfile("sim/reg_8b_tb.vcd");
		$dumpvars(0, reg_8b_tb);

		in <= 8'b01010101; clk <= 0; r <=1; #5; clk <= 1; #5;
		$display("in=%b clk=%b r=%b -> out=%b (expected 00000000)", in, clk, r, out);

		in <= 8'b01010101; clk <= 0; r <= 0; #5; clk <= 1; r <= 1; #5;
		$display("in=%b clk=%b r=%b -> out=%b (expected 00000000)", in, clk, r, out);

		in <= 8'b01010101; clk <= 0; r <= 0; #5; clk <= 1; #5;
		$display("in=%b clk=%b r=%b -> out=%b (expected 01010101)", in, clk, r, out);

		in <= 8'b11111111; clk <= 0; #5; clk <= 1; r <= 0; #5;
		$display("in=%b clk=%b r=%b -> out=%b (expected 11111111)", in, clk, r, out);
		$finish;

	end
endmodule

assets/courses/comp-arch/verilog/sim/reg_8b_tb.vcd
$date
	Fri Jul 10 12:55:47 2026
$end
$version
	Icarus Verilog
$end
$timescale
	1s
$end
$scope module reg_8b_tb $end
$var wire 8 ! out [7:0] $end
$var reg 1 " clk $end
$var reg 8 # in [7:0] $end
$var reg 1 $ r $end
$scope module uut $end
$var wire 1 " clk $end
$var wire 8 % in [7:0] $end
$var wire 1 $ r $end
$var wire 8 & out [7:0] $end
$scope module dffa0 $end
$var wire 1 ' _clk $end
$var wire 1 ( _q_or_reset $end
$var wire 1 " clk $end
$var wire 1 ) clk_n $end
$var wire 1 * d $end
$var wire 1 $ r $end
$var wire 1 + r_n $end
$var wire 1 , q_n $end
$var wire 1 - q $end
$var wire 1 . _q_n $end
$var wire 1 / _q $end
$scope module master $end
$var wire 1 * d $end
$var wire 1 0 d_n $end
$var wire 1 ) en $end
$var wire 1 1 r $end
$var wire 1 2 s $end
$var wire 1 . q_n $end
$var wire 1 / q $end
$scope module srlatch $end
$var wire 1 / q $end
$var wire 1 . q_n $end
$var wire 1 1 r $end
$var wire 1 3 r_n $end
$var wire 1 2 s $end
$var wire 1 4 s_n $end
$upscope $end
$upscope $end
$scope module slave $end
$var wire 1 ( d $end
$var wire 1 5 d_n $end
$var wire 1 ' en $end
$var wire 1 6 r $end
$var wire 1 7 s $end
$var wire 1 , q_n $end
$var wire 1 - q $end
$scope module srlatch $end
$var wire 1 - q $end
$var wire 1 , q_n $end
$var wire 1 6 r $end
$var wire 1 8 r_n $end
$var wire 1 7 s $end
$var wire 1 9 s_n $end
$upscope $end
$upscope $end
$upscope $end
$scope module dffa1 $end
$var wire 1 : _clk $end
$var wire 1 ; _q_or_reset $end
$var wire 1 " clk $end
$var wire 1 < clk_n $end
$var wire 1 = d $end
$var wire 1 $ r $end
$var wire 1 > r_n $end
$var wire 1 ? q_n $end
$var wire 1 @ q $end
$var wire 1 A _q_n $end
$var wire 1 B _q $end
$scope module master $end
$var wire 1 = d $end
$var wire 1 C d_n $end
$var wire 1 < en $end
$var wire 1 D r $end
$var wire 1 E s $end
$var wire 1 A q_n $end
$var wire 1 B q $end
$scope module srlatch $end
$var wire 1 B q $end
$var wire 1 A q_n $end
$var wire 1 D r $end
$var wire 1 F r_n $end
$var wire 1 E s $end
$var wire 1 G s_n $end
$upscope $end
$upscope $end
$scope module slave $end
$var wire 1 ; d $end
$var wire 1 H d_n $end
$var wire 1 : en $end
$var wire 1 I r $end
$var wire 1 J s $end
$var wire 1 ? q_n $end
$var wire 1 @ q $end
$scope module srlatch $end
$var wire 1 @ q $end
$var wire 1 ? q_n $end
$var wire 1 I r $end
$var wire 1 K r_n $end
$var wire 1 J s $end
$var wire 1 L s_n $end
$upscope $end
$upscope $end
$upscope $end
$scope module dffa2 $end
$var wire 1 M _clk $end
$var wire 1 N _q_or_reset $end
$var wire 1 " clk $end
$var wire 1 O clk_n $end
$var wire 1 P d $end
$var wire 1 $ r $end
$var wire 1 Q r_n $end
$var wire 1 R q_n $end
$var wire 1 S q $end
$var wire 1 T _q_n $end
$var wire 1 U _q $end
$scope module master $end
$var wire 1 P d $end
$var wire 1 V d_n $end
$var wire 1 O en $end
$var wire 1 W r $end
$var wire 1 X s $end
$var wire 1 T q_n $end
$var wire 1 U q $end
$scope module srlatch $end
$var wire 1 U q $end
$var wire 1 T q_n $end
$var wire 1 W r $end
$var wire 1 Y r_n $end
$var wire 1 X s $end
$var wire 1 Z s_n $end
$upscope $end
$upscope $end
$scope module slave $end
$var wire 1 N d $end
$var wire 1 [ d_n $end
$var wire 1 M en $end
$var wire 1 \ r $end
$var wire 1 ] s $end
$var wire 1 R q_n $end
$var wire 1 S q $end
$scope module srlatch $end
$var wire 1 S q $end
$var wire 1 R q_n $end
$var wire 1 \ r $end
$var wire 1 ^ r_n $end
$var wire 1 ] s $end
$var wire 1 _ s_n $end
$upscope $end
$upscope $end
$upscope $end
$scope module dffa3 $end
$var wire 1 ` _clk $end
$var wire 1 a _q_or_reset $end
$var wire 1 " clk $end
$var wire 1 b clk_n $end
$var wire 1 c d $end
$var wire 1 $ r $end
$var wire 1 d r_n $end
$var wire 1 e q_n $end
$var wire 1 f q $end
$var wire 1 g _q_n $end
$var wire 1 h _q $end
$scope module master $end
$var wire 1 c d $end
$var wire 1 i d_n $end
$var wire 1 b en $end
$var wire 1 j r $end
$var wire 1 k s $end
$var wire 1 g q_n $end
$var wire 1 h q $end
$scope module srlatch $end
$var wire 1 h q $end
$var wire 1 g q_n $end
$var wire 1 j r $end
$var wire 1 l r_n $end
$var wire 1 k s $end
$var wire 1 m s_n $end
$upscope $end
$upscope $end
$scope module slave $end
$var wire 1 a d $end
$var wire 1 n d_n $end
$var wire 1 ` en $end
$var wire 1 o r $end
$var wire 1 p s $end
$var wire 1 e q_n $end
$var wire 1 f q $end
$scope module srlatch $end
$var wire 1 f q $end
$var wire 1 e q_n $end
$var wire 1 o r $end
$var wire 1 q r_n $end
$var wire 1 p s $end
$var wire 1 r s_n $end
$upscope $end
$upscope $end
$upscope $end
$scope module dffa4 $end
$var wire 1 s _clk $end
$var wire 1 t _q_or_reset $end
$var wire 1 " clk $end
$var wire 1 u clk_n $end
$var wire 1 v d $end
$var wire 1 $ r $end
$var wire 1 w r_n $end
$var wire 1 x q_n $end
$var wire 1 y q $end
$var wire 1 z _q_n $end
$var wire 1 { _q $end
$scope module master $end
$var wire 1 v d $end
$var wire 1 | d_n $end
$var wire 1 u en $end
$var wire 1 } r $end
$var wire 1 ~ s $end
$var wire 1 z q_n $end
$var wire 1 { q $end
$scope module srlatch $end
$var wire 1 { q $end
$var wire 1 z q_n $end
$var wire 1 } r $end
$var wire 1 !" r_n $end
$var wire 1 ~ s $end
$var wire 1 "" s_n $end
$upscope $end
$upscope $end
$scope module slave $end
$var wire 1 t d $end
$var wire 1 #" d_n $end
$var wire 1 s en $end
$var wire 1 $" r $end
$var wire 1 %" s $end
$var wire 1 x q_n $end
$var wire 1 y q $end
$scope module srlatch $end
$var wire 1 y q $end
$var wire 1 x q_n $end
$var wire 1 $" r $end
$var wire 1 &" r_n $end
$var wire 1 %" s $end
$var wire 1 '" s_n $end
$upscope $end
$upscope $end
$upscope $end
$scope module dffa5 $end
$var wire 1 (" _clk $end
$var wire 1 )" _q_or_reset $end
$var wire 1 " clk $end
$var wire 1 *" clk_n $end
$var wire 1 +" d $end
$var wire 1 $ r $end
$var wire 1 ," r_n $end
$var wire 1 -" q_n $end
$var wire 1 ." q $end
$var wire 1 /" _q_n $end
$var wire 1 0" _q $end
$scope module master $end
$var wire 1 +" d $end
$var wire 1 1" d_n $end
$var wire 1 *" en $end
$var wire 1 2" r $end
$var wire 1 3" s $end
$var wire 1 /" q_n $end
$var wire 1 0" q $end
$scope module srlatch $end
$var wire 1 0" q $end
$var wire 1 /" q_n $end
$var wire 1 2" r $end
$var wire 1 4" r_n $end
$var wire 1 3" s $end
$var wire 1 5" s_n $end
$upscope $end
$upscope $end
$scope module slave $end
$var wire 1 )" d $end
$var wire 1 6" d_n $end
$var wire 1 (" en $end
$var wire 1 7" r $end
$var wire 1 8" s $end
$var wire 1 -" q_n $end
$var wire 1 ." q $end
$scope module srlatch $end
$var wire 1 ." q $end
$var wire 1 -" q_n $end
$var wire 1 7" r $end
$var wire 1 9" r_n $end
$var wire 1 8" s $end
$var wire 1 :" s_n $end
$upscope $end
$upscope $end
$upscope $end
$scope module dffa6 $end
$var wire 1 ;" _clk $end
$var wire 1 <" _q_or_reset $end
$var wire 1 " clk $end
$var wire 1 =" clk_n $end
$var wire 1 >" d $end
$var wire 1 $ r $end
$var wire 1 ?" r_n $end
$var wire 1 @" q_n $end
$var wire 1 A" q $end
$var wire 1 B" _q_n $end
$var wire 1 C" _q $end
$scope module master $end
$var wire 1 >" d $end
$var wire 1 D" d_n $end
$var wire 1 =" en $end
$var wire 1 E" r $end
$var wire 1 F" s $end
$var wire 1 B" q_n $end
$var wire 1 C" q $end
$scope module srlatch $end
$var wire 1 C" q $end
$var wire 1 B" q_n $end
$var wire 1 E" r $end
$var wire 1 G" r_n $end
$var wire 1 F" s $end
$var wire 1 H" s_n $end
$upscope $end
$upscope $end
$scope module slave $end
$var wire 1 <" d $end
$var wire 1 I" d_n $end
$var wire 1 ;" en $end
$var wire 1 J" r $end
$var wire 1 K" s $end
$var wire 1 @" q_n $end
$var wire 1 A" q $end
$scope module srlatch $end
$var wire 1 A" q $end
$var wire 1 @" q_n $end
$var wire 1 J" r $end
$var wire 1 L" r_n $end
$var wire 1 K" s $end
$var wire 1 M" s_n $end
$upscope $end
$upscope $end
$upscope $end
$scope module dffa7 $end
$var wire 1 N" _clk $end
$var wire 1 O" _q_or_reset $end
$var wire 1 " clk $end
$var wire 1 P" clk_n $end
$var wire 1 Q" d $end
$var wire 1 $ r $end
$var wire 1 R" r_n $end
$var wire 1 S" q_n $end
$var wire 1 T" q $end
$var wire 1 U" _q_n $end
$var wire 1 V" _q $end
$scope module master $end
$var wire 1 Q" d $end
$var wire 1 W" d_n $end
$var wire 1 P" en $end
$var wire 1 X" r $end
$var wire 1 Y" s $end
$var wire 1 U" q_n $end
$var wire 1 V" q $end
$scope module srlatch $end
$var wire 1 V" q $end
$var wire 1 U" q_n $end
$var wire 1 X" r $end
$var wire 1 Z" r_n $end
$var wire 1 Y" s $end
$var wire 1 [" s_n $end
$upscope $end
$upscope $end
$scope module slave $end
$var wire 1 O" d $end
$var wire 1 \" d_n $end
$var wire 1 N" en $end
$var wire 1 ]" r $end
$var wire 1 ^" s $end
$var wire 1 S" q_n $end
$var wire 1 T" q $end
$scope module srlatch $end
$var wire 1 T" q $end
$var wire 1 S" q_n $end
$var wire 1 ]" r $end
$var wire 1 _" r_n $end
$var wire 1 ^" s $end
$var wire 1 `" s_n $end
$upscope $end
$upscope $end
$upscope $end
$upscope $end
$upscope $end
$enddefinitions $end
$comment Show the parameter values. $end
$dumpall
$end
#0
$dumpvars
1`"
0_"
0^"
1]"
1\"
1["
0Z"
0Y"
1X"
1W"
0V"
1U"
0T"
1S"
0R"
0Q"
1P"
0O"
1N"
1M"
0L"
0K"
1J"
1I"
0H"
1G"
1F"
0E"
0D"
1C"
0B"
0A"
1@"
0?"
1>"
1="
0<"
1;"
1:"
09"
08"
17"
16"
15"
04"
03"
12"
11"
00"
1/"
0."
1-"
0,"
0+"
1*"
0)"
1("
1'"
0&"
0%"
1$"
1#"
0""
1!"
1~
0}
0|
1{
0z
0y
1x
0w
1v
1u
0t
1s
1r
0q
0p
1o
1n
1m
0l
0k
1j
1i
0h
1g
0f
1e
0d
0c
1b
0a
1`
1_
0^
0]
1\
1[
0Z
1Y
1X
0W
0V
1U
0T
0S
1R
0Q
1P
1O
0N
1M
1L
0K
0J
1I
1H
1G
0F
0E
1D
1C
0B
1A
0@
1?
0>
0=
1<
0;
1:
19
08
07
16
15
04
13
12
01
00
1/
0.
0-
1,
0+
1*
1)
0(
1'
b0 &
b1010101 %
1$
b1010101 #
0"
b0 !
$end
#5
14
1F
1Z
1l
1""
14"
1H"
1Z"
02
0D
0X
0j
0~
02"
0F"
0X"
0)
0<
0O
0b
0u
0*"
0="
0P"
1"
#10
05
0[
0#"
0I"
04
18
0F
1K
0Z
1^
0l
1q
0""
1&"
04"
19"
0H"
1L"
0Z"
1_"
1(
1N
1t
1<"
12
06
1D
0I
1X
0\
1j
0o
1~
0$"
12"
07"
1F"
0J"
1X"
0]"
1+
1>
1Q
1d
1w
1,"
1?"
1R"
1)
0'
1<
0:
1O
0M
1b
0`
1u
0s
1*"
0("
1="
0;"
1P"
0N"
0$
0"
#15
08
0^
0&"
0L"
1,
1R
1x
1@"
16
1\
1$"
1J"
0-
0S
0y
b0 !
b0 &
0A"
15
1[
1#"
1I"
14
19
1F
0K
1Z
1_
1l
0q
1""
1'"
14"
09"
1H"
1M"
1Z"
0_"
0(
0N
0t
0<"
02
07
0D
1I
0X
0]
0j
1o
0~
0%"
02"
17"
0F"
0K"
0X"
1]"
0+
0>
0Q
0d
0w
0,"
0?"
0R"
0)
1'
0<
1:
0O
1M
0b
1`
0u
1s
0*"
1("
0="
1;"
0P"
1N"
1$
1"
#20
05
0[
0#"
0I"
04
18
0F
1K
0Z
1^
0l
1q
0""
1&"
04"
19"
0H"
1L"
0Z"
1_"
1(
1N
1t
1<"
12
06
1D
0I
1X
0\
1j
0o
1~
0$"
12"
07"
1F"
0J"
1X"
0]"
1+
1>
1Q
1d
1w
1,"
1?"
1R"
1)
0'
1<
0:
1O
0M
1b
0`
1u
0s
1*"
0("
1="
0;"
1P"
0N"
0$
0"
#25
0,
0R
0x
0@"
1-
1S
1y
b1010101 !
b1010101 &
1A"
14
09
1F
0K
1Z
0_
1l
0q
1""
0'"
14"
09"
1H"
0M"
1Z"
0_"
02
17
0D
1I
0X
1]
0j
1o
0~
1%"
02"
17"
0F"
1K"
0X"
1]"
0)
1'
0<
1:
0O
1M
0b
1`
0u
1s
0*"
1("
0="
1;"
0P"
1N"
1"
#30
0H
0n
06"
0\"
0A
1;
0g
1a
0/"
1)"
0U"
1O"
1B
1h
10"
1V"
04
19
1K
0Z
1_
1q
0""
1'"
19"
0H"
1M"
1_"
0G
0m
05"
0["
12
07
0I
1X
0]
0o
1~
0%"
07"
1F"
0K"
0]"
0C
1E
0i
1k
01"
13"
0W"
1Y"
1)
0'
1<
0:
1O
0M
1b
0`
1u
0s
1*"
0("
1="
0;"
1P"
0N"
1=
1c
1+"
1Q"
0"
b11111111 #
b11111111 %
#35
0?
0e
0-"
0S"
1@
1f
1."
b11111111 !
b11111111 &
1T"
14
09
1G
0L
1Z
0_
1m
0r
1""
0'"
15"
0:"
1H"
0M"
1["
0`"
02
17
0E
1J
0X
1]
0k
1p
0~
1%"
03"
18"
0F"
1K"
0Y"
1^"
0)
1'
0<
1:
0O
1M
0b
1`
0u
1s
0*"
1("
0="
1;"
0P"
1N"
1"
